hlink/__init__.py
hlink/errors.py
hlink/configs/__init__.py
hlink/configs/load_config.py
hlink/linking/README.md
hlink/linking/__init__.py
hlink/linking/link_run.py
hlink/linking/link_step.py
hlink/linking/link_task.py
hlink/linking/table.py
hlink/linking/table_definitions.csv
hlink/linking/util.py
hlink/linking/core/__init__.py
hlink/linking/core/classifier.py
hlink/linking/core/column_mapping.py
hlink/linking/core/comparison.py
hlink/linking/core/comparison_feature.py
hlink/linking/core/dist_table.py
hlink/linking/core/model_metrics.py
hlink/linking/core/pipeline.py
hlink/linking/core/substitutions.py
hlink/linking/core/threshold.py
hlink/linking/core/transforms.py
hlink/linking/hh_matching/__init__.py
hlink/linking/hh_matching/hh_matching.py
hlink/linking/hh_matching/link_step_block_on_households.py
hlink/linking/hh_matching/link_step_filter.py
hlink/linking/hh_matching/templates/hh_blocked_matches.sql
hlink/linking/hh_matching/templates/hh_potential_matches.sql
hlink/linking/hh_model_exploration/__init__.py
hlink/linking/hh_model_exploration/hh_model_exploration.py
hlink/linking/hh_model_exploration/templates/.gitkeep
hlink/linking/hh_training/__init__.py
hlink/linking/hh_training/hh_training.py
hlink/linking/hh_training/templates/.gitkeep
hlink/linking/matching/__init__.py
hlink/linking/matching/link_step_explode.py
hlink/linking/matching/link_step_match.py
hlink/linking/matching/link_step_score.py
hlink/linking/matching/matching.py
hlink/linking/matching/templates/potential_matches.sql
hlink/linking/matching/templates/potential_matches_count.sql
hlink/linking/matching/templates/potential_matches_universe.sql
hlink/linking/model_exploration/__init__.py
hlink/linking/model_exploration/link_step_create_features.py
hlink/linking/model_exploration/link_step_ingest_file.py
hlink/linking/model_exploration/link_step_train_test_models.py
hlink/linking/model_exploration/model_exploration.py
hlink/linking/model_exploration/templates/.gitkeep
hlink-4.2.2.dist-info/licenses/LICENSE.txt
hlink-4.2.2.dist-info/METADATA
hlink-4.2.2.dist-info/WHEEL
hlink-4.2.2.dist-info/entry_points.txt
hlink-4.2.2.dist-info/top_level.txt
hlink-4.2.2.dist-info/RECORD
