Metadata-Version: 2.4
Name: hlink
Version: 4.2.2
Summary: Fast supervised pyspark record linkage software
License-Expression: MPL-2.0-no-copyleft-exception
Project-URL: Homepage, https://github.com/ipums/hlink
Project-URL: Documentation, https://hlink.docs.ipums.org
Project-URL: Repository, https://github.com/ipums/hlink
Project-URL: Changelog, https://hlink.docs.ipums.org/changelog.html
Classifier: Programming Language :: Python :: 3
Classifier: Programming Language :: Python :: 3.10
Classifier: Programming Language :: Python :: 3.11
Classifier: Programming Language :: Python :: 3.12
Requires-Python: >=3.10
License-File: LICENSE.txt
Requires-Dist: colorama>=0.4.6
Requires-Dist: ipython>=8.3.0
Requires-Dist: Jinja2>=3.1.0
Requires-Dist: numpy>=1.22.0
Requires-Dist: pandas>=1.4.0
Requires-Dist: pyspark~=3.5.0
Requires-Dist: scikit-learn>=1.1.0
Requires-Dist: toml>=0.10.0
Requires-Dist: tomli>=2.0
Provides-Extra: dev
Requires-Dist: pytest>=7.1.0; extra == "dev"
Requires-Dist: hypothesis>=6.0; extra == "dev"
Requires-Dist: black>=23.0; extra == "dev"
Requires-Dist: flake8>=5.0; extra == "dev"
Requires-Dist: pre-commit>=2.0; extra == "dev"
Requires-Dist: twine>=4.0; extra == "dev"
Requires-Dist: build>=0.6; extra == "dev"
Requires-Dist: setuptools>=71.0; extra == "dev"
Requires-Dist: sphinx; extra == "dev"
Requires-Dist: recommonmark; extra == "dev"
Provides-Extra: docs
Requires-Dist: sphinx; extra == "docs"
Requires-Dist: recommonmark; extra == "docs"
Provides-Extra: lightgbm
Requires-Dist: synapseml>=1.0; extra == "lightgbm"
Provides-Extra: xgboost
Requires-Dist: xgboost>=2.0; extra == "xgboost"
Requires-Dist: pyarrow>=4.0; extra == "xgboost"
Dynamic: license-file
